pycreate2/OI.py
pycreate2/__init__.py
pycreate2/bin/create_monitor.py
pycreate2/bin/create_reset.py
pycreate2/bin/create_shutdown.py
pycreate2/create2api.py
pycreate2/createSerial.py
pycreate2/packets.py
pycreate2-0.7.6.dist-info/entry_points.txt
pycreate2-0.7.6.dist-info/WHEEL
pycreate2-0.7.6.dist-info/METADATA
pycreate2-0.7.6.dist-info/RECORD
