Metadata-Version: 2.1
Name: pycreate2
Version: 0.7.6
Summary: A library to control iRobot Create 2 with python
Home-page: https://pypi.org/project/pycreate2/
License: MIT
Keywords: roomba,irobot,create 2,api,framework,library,robotics,robot
Author: walchko
Author-email: walchko@users.noreply.github.com
Requires-Python: >=3.6
Classifier: Development Status :: 4 - Beta
Classifier: Intended Audience :: Developers
Classifier: License :: OSI Approved :: MIT License
Classifier: Operating System :: OS Independent
Classifier: Programming Language :: Python :: 3
Classifier: Programming Language :: Python :: 3.6
Classifier: Programming Language :: Python :: 3.7
Classifier: Programming Language :: Python :: 3.8
Classifier: Topic :: Software Development :: Libraries
Classifier: Topic :: Software Development :: Libraries :: Application Frameworks
Classifier: Topic :: Software Development :: Libraries :: Python Modules
Requires-Dist: colorama
Requires-Dist: importlib-metadata
Requires-Dist: pyserial (>=3.4,<4.0)
Requires-Dist: simplejson
Project-URL: Repository, https://github.com/MomsFriendlyRobotCompany/pycreate2
